expat_fatcat/__init__.py
expat_fatcat/expat_fatcat.py
expat_fatcat-0.2.5.dist-info/LICENSE
expat_fatcat-0.2.5.dist-info/METADATA
expat_fatcat-0.2.5.dist-info/WHEEL
expat_fatcat-0.2.5.dist-info/top_level.txt
expat_fatcat-0.2.5.dist-info/RECORD
