Metadata-Version: 2.1
Name: expat-fatcat
Version: 0.2.5
Summary: expat-fatcat helps US taxpayers living abroad with FX coversions for their tax returns.
Home-page: https://github.com/munichpavel/expat_fatcat
Author: Paul Larsen
Author-email: munichpavel@gmail.com
License: MIT license
Keywords: expat_fatcat
Platform: UNKNOWN
Requires-Python: >3.6
Requires-Dist: quandl
Requires-Dist: pandas
